{"id": "Q677864", "description": "quantum mechanical model of a particle in a harmonic potential well", "label": "quantenmechanischer harmonischer Oszillator", "aliases": ["harmonische Oszillator in der Quantenmechanik"], "instance_of": ["Modell, welches nach wissenschaftlichen Kriterien, Ph\u00e4nomene erkl\u00e4rt"], "subclass_of": ["schwingungsf\u00e4higes System mit linearer R\u00fcckstellgr\u00f6\u00dfe"], "types": ["Modell, welches nach wissenschaftlichen Kriterien, Ph\u00e4nomene erkl\u00e4rt"], "subclasses": ["schwingungsf\u00e4higes System mit linearer R\u00fcckstellgr\u00f6\u00dfe"]}