{"id": "Q83219", "description": "scientific laws describing motion of planets around the Sun", "label": "Kepler's laws of planetary motion", "aliases": ["Kepler's laws"], "instance_of": ["scientific law of physics"], "types": ["scientific law of physics"], "image_url": "https://commons.wikimedia.org/wiki/Special:FilePath/Plocha_pruvodice.png", "has_parts": ["physica law that planetary orbits are ellipses with the Sun at one focus", "physical law that a line segment joining a planet and the Sun sweeps out equal areas during equal intervals of time", "physical law that the square of a planet\u2019s orbital period is proportional to the cube of the orbit\u2019s semimajor axis"], "gnd_id": "4365820-9"}