{"id": "Q133673", "description": "Eigendrehimpuls von Teilchen", "label": "Spin", "subclass_of": ["physikalische Erhaltungsgr\u00f6\u00dfe", "Art von Eigenschaft", "quantitativ bestimmbare Eigenschaft eines physikalischen Objektes, Vorgangs oder Zustands", "Gr\u00f6\u00dfe, die einen Richtungscharakter besitzt"], "subclasses": ["physikalische Erhaltungsgr\u00f6\u00dfe", "Art von Eigenschaft", "quantitativ bestimmbare Eigenschaft eines physikalischen Objektes, Vorgangs oder Zustands", "Gr\u00f6\u00dfe, die einen Richtungscharakter besitzt"], "image_url": "https://commons.wikimedia.org/wiki/Special:FilePath/\"Father\"_and_\"Mother\"_of_the_series_\"Spin_Family\".jpg", "gnd_id": "4125988-9"}